retejo/__init__.py
retejo/bind_method.py
retejo/errors.py
retejo/file_obj.py
retejo/py.typed
retejo/request_context_builder.py
retejo/_internal/__init__.py
retejo/_internal/bind_method.py
retejo/_internal/parents_resolver.py
retejo/_internal/singlton.py
retejo/_internal/_adaptix/__init__.py
retejo/_internal/_adaptix/common.py
retejo/_internal/_adaptix/feature_requirement.py
retejo/_internal/_adaptix/type_tools/__init__.py
retejo/_internal/_adaptix/type_tools/basic_utils.py
retejo/_internal/_adaptix/type_tools/constants.py
retejo/_internal/_adaptix/type_tools/fundamentals.py
retejo/_internal/_adaptix/type_tools/generic_resolver.py
retejo/_internal/_adaptix/type_tools/implicit_params.py
retejo/_internal/_adaptix/type_tools/norm_utils.py
retejo/_internal/_adaptix/type_tools/normalize_type.py
retejo/_internal/_adaptix/type_tools/type_evaler.py
retejo/_internal/interfaces/__init__.py
retejo/_internal/interfaces/client.py
retejo/_internal/interfaces/factory.py
retejo/_internal/interfaces/request_context_builder.py
retejo/_internal/interfaces/sendable_method.py
retejo/_internal/interfaces/sendable_request.py
retejo/_internal/markers/__init__.py
retejo/_internal/markers/base.py
retejo/_internal/markers/body.py
retejo/_internal/markers/file.py
retejo/_internal/markers/header.py
retejo/_internal/markers/omitted.py
retejo/_internal/markers/query_param.py
retejo/_internal/markers/url_var.py
retejo/_internal/method/__init__.py
retejo/_internal/method/context.py
retejo/_internal/method/method.py
retejo/integrations/__init__.py
retejo/integrations/adaptix/__init__.py
retejo/integrations/adaptix/aiohttp.py
retejo/integrations/adaptix/base.py
retejo/integrations/adaptix/requests.py
retejo/integrations/common/__init__.py
retejo/integrations/common/aiohttp.py
retejo/integrations/common/base.py
retejo/integrations/common/requests.py
retejo/integrations/pydantic/__init__.py
retejo/integrations/pydantic/base.py
retejo/interfaces/__init__.py
retejo/markers/__init__.py
retejo-0.0.4.dist-info/licenses/LICENSE
retejo-0.0.4.dist-info/METADATA
retejo-0.0.4.dist-info/WHEEL
retejo-0.0.4.dist-info/top_level.txt
retejo-0.0.4.dist-info/RECORD
